libflowcam/__init__.py
libflowcam/native_interface.py
libflowcam/utils.py
libflowcam-0.5.dist-info/licenses/LICENSE
libflowcam-0.5.dist-info/METADATA
libflowcam-0.5.dist-info/WHEEL
libflowcam-0.5.dist-info/top_level.txt
libflowcam-0.5.dist-info/RECORD
