Metadata-Version: 2.4
Name: libflowcam
Version: 0.5
Summary: A Python module for interacting with IFCB data.
Author-email: Alex Baldwin <contact@alexbaldwin.dev>
License: LGPL-3.0
Project-URL: Homepage, https://github.com/NOC-OI/libflowcam
Project-URL: Issues, https://github.com/NOC-OI/libflowcam/issues
Classifier: Programming Language :: Python :: 3
Classifier: Operating System :: OS Independent
Requires-Python: >=3.6
License-File: LICENSE
Requires-Dist: numpy>=1.13.3
Requires-Dist: pillow>=8.3.1
Dynamic: license-file
